strudra/__init__.py
strudra/strudra.py
strudra-0.1.2.dist-info/LICENSE
strudra-0.1.2.dist-info/METADATA
strudra-0.1.2.dist-info/WHEEL
strudra-0.1.2.dist-info/top_level.txt
strudra-0.1.2.dist-info/RECORD
