Metadata-Version: 2.1
Name: strudra
Version: 0.1.2
Summary: Craft Ghidra structs in python
Home-page: https://github.com/domenukk/strudra
Author: domenukk
Author-email: mail@dmnk.co
License: UNKNOWN
Platform: UNKNOWN
Classifier: Development Status :: 3 - Alpha
Classifier: License :: OSI Approved :: MIT License
Classifier: Programming Language :: Python :: 3.6
Classifier: Programming Language :: Python :: 3.7
Classifier: Programming Language :: Python :: 3.8
Classifier: Programming Language :: Python :: 3.9
Requires-Dist: ghidra-bridge
